MANIFEST.in
README.md
setup.py
trustpilot_authenticated_encryption/__init__.py
trustpilot_authenticated_encryption/encryption.py
trustpilot_authenticated_encryption.egg-info/PKG-INFO
trustpilot_authenticated_encryption.egg-info/SOURCES.txt
trustpilot_authenticated_encryption.egg-info/dependency_links.txt
trustpilot_authenticated_encryption.egg-info/requires.txt
trustpilot_authenticated_encryption.egg-info/top_level.txt