Metadata-Version: 1.0
Name: trustpilot-authenticated-encryption
Version: 1.0.2
Summary: Library for authenticated encryption used with Trustpilot
Home-page: https://github.com/trustpilot/python-authenticated-encryption
Author: Trustpilot
Author-email: UNKNOWN
License: MIT
Platform: UNKNOWN
